copyriot/__init__.py
copyriot/__main__.py
copyriot/copyriot.py
copyriot-0.1.3.dist-info/LICENCE
copyriot-0.1.3.dist-info/METADATA
copyriot-0.1.3.dist-info/WHEEL
copyriot-0.1.3.dist-info/entry_points.txt
copyriot-0.1.3.dist-info/top_level.txt
copyriot-0.1.3.dist-info/RECORD
