Metadata-Version: 2.1
Name: copyriot
Version: 0.1.3
Summary: Generate copyright headers to files
Author: Jeeeun Evans
Author-email: jeeeun.evans@codethink.co.uk
License: GPLv3
Keywords: copyright,license
Classifier: Programming Language :: Python :: 3
Classifier: License :: OSI Approved :: GNU General Public License v3 or later (GPLv3+)
Classifier: Operating System :: OS Independent
Classifier: Environment :: X11 Applications
Classifier: Intended Audience :: System Administrators
Classifier: Intended Audience :: Developers
Classifier: Operating System :: POSIX
Classifier: Operating System :: POSIX :: Linux
Requires-Python: >=3.8
License-File: LICENCE
